Combinational_Circuits/Full_Adder.sv
module Full_Adder (
    input A,B,Cin,
    output S,Cout
);

    assign S = A ^ B ^ Cin;
    assign Cout = Cin & (A ^ B) || (A & B);
    
endmodule

Combinational_Circuits/Full_Adder_tb.sv
module Full_Adder_tb ();
    reg A;
    reg B;
    reg Cin;
    wire S;
    wire Cout;

    Full_Adder Full_Adder0(.A(A),.B(B),.Cin(Cin),.S(S),.Cout(Cout));

    initial begin

        #10 A = 0; B = 0; Cin = 0;
        #10 A = 0; B = 0; Cin = 1; 
        #10 A = 0; B = 1; Cin = 0;
        #10 A = 0; B = 1; Cin = 1;
        #10 A = 1; B = 0; Cin = 0;
        #10 A = 1; B = 0; Cin = 1;
        #10 A = 1; B = 1; Cin = 0;
        #10 A = 1; B = 1; Cin = 1;

        #100 $finish;
    end

    initial begin

        $monitor("Time=%0t A=%b B=%b Cin=%b Cout=%b sum=%b",
                 $time, A, B, Cin, Cout,S);

        $dumpfile("wave.vcd");
        $dumpvars(0, Full_Adder_tb);
        
    end

endmodule

Combinational_Circuits/wave.vcd
$date
	Sun May 31 18:51:56 2026
$end
$version
	Icarus Verilog
$end
$timescale
	1s
$end
$scope module Full_Adder_tb $end
$var wire 1 ! S $end
$var wire 1 " Cout $end
$var reg 1 # A $end
$var reg 1 $ B $end
$var reg 1 % Cin $end
$scope module Full_Adder0 $end
$var wire 1 # A $end
$var wire 1 $ B $end
$var wire 1 % Cin $end
$var wire 1 " Cout $end
$var wire 1 ! S $end
$upscope $end
$upscope $end
$enddefinitions $end
$comment Show the parameter values. $end
$dumpall
$end
#0
$dumpvars
x%
x$
x#
x"
x!
$end
#10
0"
0!
0%
0$
0#
#20
1!
1%
#30
0%
1$
#40
1"
0!
1%
#50
0"
1!
0%
0$
1#
#60
1"
0!
1%
#70
0%
1$
#80
1!
1%
