Sequential_Circuits/flip_flop.sv
module flip_flop (
    input clk,
    input resetn,
    input d,
    output reg q);

    always @(posedge clk)

        if (!resetn)
            q <= 0;
        else
            q <= d;
    
endmodule

Sequential_Circuits/tb_top.sv
module tb_top ();

    reg clk;
    reg resetn;
    reg d;
    wire q;

    flip_flop flip_flop0(.clk(clk),.resetn(resetn),.d(d),.q(q));

    always #10 clk <= ~clk;

    initial begin
        resetn <= 0;
        clk <= 0;
        d <= 0;

        #10 resetn <= 1;
        #5       d <= 1;
        #8       d <= 0;
        #2       d <= 1;
        #10      d <= 0;

        #50 $finish;
    end

    initial begin
        $monitor("Time=%0t clk=%b resetn=%b d=%b q=%b",
                 $time, clk, resetn, d, q);
    end

    initial begin
    $dumpfile("wave.vcd");
    $dumpvars(0, tb_top);
end
    
endmodule

Sequential_Circuits/wave.vcd
$date
	Sun May 31 10:53:30 2026
$end
$version
	Icarus Verilog
$end
$timescale
	1s
$end
$scope module tb_top $end
$var wire 1 ! q $end
$var reg 1 " clk $end
$var reg 1 # d $end
$var reg 1 $ resetn $end
$scope module flip_flop0 $end
$var wire 1 " clk $end
$var wire 1 # d $end
$var wire 1 $ resetn $end
$var reg 1 ! q $end
$upscope $end
$upscope $end
$enddefinitions $end
$comment Show the parameter values. $end
$dumpall
$end
#0
$dumpvars
0$
0#
0"
x!
$end
#10
0!
1$
1"
#15
1#
#20
0"
#23
0#
#25
1#
#30
1!
1"
#35
0#
#40
0"
#50
0!
1"
